zhengshang/__init__.py
zhengshang/template_zhengshang.xlsx
zhengshang-0.1.2.dist-info/METADATA
zhengshang-0.1.2.dist-info/WHEEL
zhengshang-0.1.2.dist-info/entry_points.txt
zhengshang-0.1.2.dist-info/licenses/LICENSE.txt
zhengshang-0.1.2.dist-info/RECORD
